serapis/__init__.py
serapis/calibration.py
serapis/crosssection.py
serapis/event.py
serapis/inputs.py
serapis/interface.py
serapis/river.py
serapis/saintvenant.py
serapis/serapis_warnings.py
serapis/plot/__init__.py
serapis/plot/visualizer.py
serapis-0.2.0.dist-info/licenses/LICENSE.md
serapis-0.2.0.dist-info/METADATA
serapis-0.2.0.dist-info/WHEEL
serapis-0.2.0.dist-info/top_level.txt
serapis-0.2.0.dist-info/RECORD
