Metadata-Version: 2.4
Name: serapis
Version: 0.2.0
Summary: Flood simulation model
Author-email: Mostafa Farrag <moah.farrag@gmail.com>
License: GNU General Public License v3
Project-URL: homepage, https://github.com/Serapieum-of-alex/serapis
Project-URL: repository, https://github.com/Serapieum-of-alex/serapis
Project-URL: documentation, https://serapieum-of-alex.github.io/serapis
Project-URL: Changelog, https://github.com/Serapieum-of-alex/serapis/docs/change-log.md
Keywords: Hydraulics,Flood model,Inundation model
Classifier: Development Status :: 5 - Production/Stable
Classifier: Environment :: Console
Classifier: License :: OSI Approved :: GNU General Public License v3 (GPLv3)
Classifier: Natural Language :: English
Classifier: Programming Language :: Python :: 3
Classifier: Programming Language :: Python :: 3.11
Classifier: Programming Language :: Python :: 3.12
Classifier: Programming Language :: Python :: 3.13
Classifier: Topic :: Scientific/Engineering :: GIS
Classifier: Intended Audience :: Science/Research
Classifier: Intended Audience :: Developers
Requires-Python: <4,>=3.11
License-File: LICENSE.md
Requires-Dist: geopandas>=1.0.0
Requires-Dist: numpy>=2.0.0
Requires-Dist: pandas>=2.0.0
Requires-Dist: loguru>=0.7.3
Requires-Dist: cleopatra==0.6.0
Requires-Dist: pyramids-gis==0.8.0
Requires-Dist: serapeum_utils==0.2.0
Requires-Dist: statista==0.6.3
Requires-Dist: matplotlib>=3.7.2
Requires-Dist: statsmodels>=0.14.1
Provides-Extra: dev
Requires-Dist: nbval>=0.11.0; extra == "dev"
Requires-Dist: pre-commit>=3.7.1; extra == "dev"
Requires-Dist: pre-commit-hooks>=4.6.0; extra == "dev"
Requires-Dist: pytest>=8.2.2; extra == "dev"
Requires-Dist: pytest-cov>=5.0.0; extra == "dev"
Requires-Dist: coverage; extra == "dev"
Requires-Dist: build>=1.0.0; extra == "dev"
Requires-Dist: twine>=5.0.0; extra == "dev"
Requires-Dist: pip; extra == "dev"
Requires-Dist: jupyterlab; extra == "dev"
Requires-Dist: notebook; extra == "dev"
Requires-Dist: jupyter; extra == "dev"
Requires-Dist: commitizen>=4.8.4; extra == "dev"
Requires-Dist: mypy>=1.19.0; extra == "dev"
Provides-Extra: docs
Requires-Dist: mkdocs>=1.5.3; extra == "docs"
Requires-Dist: mkdocs-material>=9.5.3; extra == "docs"
Requires-Dist: mkdocstrings>=0.24.0; extra == "docs"
Requires-Dist: mkdocstrings-python>=1.7.5; extra == "docs"
Requires-Dist: mike>=2.1.3; extra == "docs"
Requires-Dist: mkdocs-jupyter>=0.25.1; extra == "docs"
Requires-Dist: mkdocs-autorefs>=1.2; extra == "docs"
Requires-Dist: mkdocs-macros-plugin>=1.3.7; extra == "docs"
Requires-Dist: mkdocs-table-reader-plugin>=3.1.0; extra == "docs"
Requires-Dist: mkdocs-mermaid2-plugin>=1.2.1; extra == "docs"
Requires-Dist: jupyter-contrib-nbextensions>=0.7.0; extra == "docs"
Requires-Dist: mkdocs-panzoom-plugin; extra == "docs"
Requires-Dist: notebook<7.0; extra == "docs"
Dynamic: license-file
